{
  "generated_at": "2026-03-05T22:22:11.695282+02:00",
  "tarbutu_url": "https://www.tarbutu.co.il/%D7%A7%D7%A8%D7%95%D7%96%D7%99%D7%9D/",
  "massaot_url": "https://www.masaot.co.il/",
  "tarbutu_cruises": [
    {
      "source": "תרבותו",
      "title": "טיולים יבשתיים",
      "ship": null,
      "ship_normalized": "",
      "date_display": "9 ימים  - נובמבר 2026",
      "date_norm": [
        2026,
        11
      ],
      "price": null,
      "url": "https://tarbutu.co.il/%d7%98%d7%99%d7%95%d7%9c%d7%99-%d7%aa%d7%a8%d7%91%d7%95%d7%aa/"
    },
    {
      "source": "תרבותו",
      "title": "קרנבל המסיכות בוונציה",
      "ship": null,
      "ship_normalized": "",
      "date_display": "9 ימים  - נובמבר 2026",
      "date_norm": [
        2026,
        11
      ],
      "price": null,
      "url": "https://tarbutu.co.il/%d7%a1%d7%9e%d7%99%d7%a0%d7%a8-%d7%9e%d7%98%d7%99%d7%99%d7%9c-%d7%9c%d7%95%d7%a0%d7%a6%d7%99%d7%94-%d7%91%d7%a7%d7%a8%d7%a0%d7%91%d7%9c/"
    },
    {
      "source": "תרבותו",
      "title": "צפון קוריאה וחבל מנצ’וריה בסין",
      "ship": null,
      "ship_normalized": "",
      "date_display": "9 ימים  - נובמבר 2026",
      "date_norm": [
        2026,
        11
      ],
      "price": null,
      "url": "https://tarbutu.co.il/%d7%98%d7%99%d7%95%d7%9c-%d7%9e%d7%90%d7%95%d7%a8%d7%92%d7%9f-%d7%9c%d7%a6%d7%a4%d7%95%d7%9f-%d7%a7%d7%95%d7%a8%d7%99%d7%90%d7%94-%d7%95%d7%97%d7%91%d7%9c-%d7%9e%d7%a0%d7%a6%d7%95%d7%a8%d7%99%d7%94/"
    },
    {
      "source": "תרבותו",
      "title": "צפון קוריאה",
      "ship": null,
      "ship_normalized": "",
      "date_display": "9 ימים  - נובמבר 2026",
      "date_norm": [
        2026,
        11
      ],
      "price": null,
      "url": "https://tarbutu.co.il/%d7%98%d7%99%d7%95%d7%9c-%d7%9c%d7%a6%d7%a4%d7%95%d7%9f-%d7%a7%d7%95%d7%a8%d7%99%d7%90%d7%94/"
    },
    {
      "source": "תרבותו",
      "title": "פרו, אקוודור ושייט באיי גלאפגוס",
      "ship": null,
      "ship_normalized": "",
      "date_display": "9 ימים  - נובמבר 2026",
      "date_norm": [
        2026,
        11
      ],
      "price": null,
      "url": "https://tarbutu.co.il/%d7%98%d7%99%d7%95%d7%9c%d7%99-%d7%a2%d7%95%d7%9e%d7%a7-%d7%9c%d7%a4%d7%a8%d7%95-%d7%95%d7%90%d7%a7%d7%95%d7%95%d7%93%d7%95%d7%a8/"
    },
    {
      "source": "תרבותו",
      "title": "פרו, אקוודור, מאצ’ו פיצ’ו, אמזונס ושייט באיי גלאפגוס",
      "ship": null,
      "ship_normalized": "",
      "date_display": "9 ימים  - נובמבר 2026",
      "date_norm": [
        2026,
        11
      ],
      "price": null,
      "url": "https://tarbutu.co.il/%d7%98%d7%99%d7%95%d7%9c-%d7%9e%d7%90%d7%95%d7%a8%d7%92%d7%9f-%d7%9c%d7%93%d7%a8%d7%95%d7%9d-%d7%90%d7%9e%d7%a8%d7%99%d7%a7%d7%94-%d7%9b%d7%95%d7%9c%d7%9c-%d7%a9%d7%99%d7%99%d7%98-%d7%99%d7%90%d7%9b/"
    },
    {
      "source": "תרבותו",
      "title": "לפלנד – ספארי חורף",
      "ship": null,
      "ship_normalized": "",
      "date_display": "9 ימים  - נובמבר 2026",
      "date_norm": [
        2026,
        11
      ],
      "price": null,
      "url": "https://tarbutu.co.il/%d7%9c%d7%a4%d7%9c%d7%a0%d7%93/"
    },
    {
      "source": "תרבותו",
      "title": "קרוזים",
      "ship": null,
      "ship_normalized": "",
      "date_display": "9 ימים  - נובמבר 2026",
      "date_norm": [
        2026,
        11
      ],
      "price": null,
      "url": "https://tarbutu.co.il/%d7%a7%d7%a8%d7%95%d7%96%d7%99%d7%9d/"
    },
    {
      "source": "תרבותו",
      "title": "טיול ליפן כולל קרוז",
      "ship": null,
      "ship_normalized": "",
      "date_display": "9 ימים  - נובמבר 2026",
      "date_norm": [
        2026,
        11
      ],
      "price": null,
      "url": "https://tarbutu.co.il/%d7%98%d7%99%d7%95%d7%9c%d7%99%d7%9d-%d7%9c%d7%99%d7%a4%d7%9f/"
    },
    {
      "source": "תרבותו",
      "title": "אוסטרליה וניו זילנד",
      "ship": null,
      "ship_normalized": "",
      "date_display": "9 ימים  - נובמבר 2026",
      "date_norm": [
        2026,
        11
      ],
      "price": null,
      "url": "https://tarbutu.co.il/%d7%a7%d7%a8%d7%95%d7%96%d7%99%d7%9d-%d7%9c%d7%90%d7%95%d7%a1%d7%98%d7%a8%d7%9c%d7%99%d7%94-%d7%95%d7%a0%d7%99%d7%95-%d7%96%d7%99%d7%9c%d7%a0%d7%93/"
    },
    {
      "source": "תרבותו",
      "title": "איסלנד והאיים הבריטים",
      "ship": null,
      "ship_normalized": "",
      "date_display": "9 ימים  - נובמבר 2026",
      "date_norm": [
        2026,
        11
      ],
      "price": null,
      "url": "https://tarbutu.co.il/%d7%a7%d7%a8%d7%95%d7%96%d7%99%d7%9d-%d7%9c%d7%90%d7%99%d7%a1%d7%9c%d7%a0%d7%93-%d7%95%d7%94%d7%90%d7%99%d7%99%d7%9d-%d7%94%d7%91%d7%a8%d7%99%d7%98%d7%99%d7%9d/"
    },
    {
      "source": "תרבותו",
      "title": "איסלנד והפיורדים הנורבגיים-מיוחד!",
      "ship": null,
      "ship_normalized": "",
      "date_display": "9 ימים  - נובמבר 2026",
      "date_norm": [
        2026,
        11
      ],
      "price": null,
      "url": "https://tarbutu.co.il/%d7%a7%d7%a8%d7%95%d7%96-%d7%9e%d7%90%d7%95%d7%a8%d7%92%d7%9f-%d7%90%d7%9c-%d7%a4%d7%9c%d7%90%d7%99-%d7%94%d7%98%d7%91%d7%a2-%d7%a9%d7%9c-%d7%90%d7%99%d7%a1%d7%9c%d7%a0%d7%93-%d7%95%d7%94%d7%a4%d7%99/"
    },
    {
      "source": "תרבותו",
      "title": "האיים הבריטיים",
      "ship": null,
      "ship_normalized": "",
      "date_display": "9 ימים  - נובמבר 2026",
      "date_norm": [
        2026,
        11
      ],
      "price": null,
      "url": "https://tarbutu.co.il/%d7%a7%d7%a8%d7%95%d7%96%d7%99%d7%9d-%d7%9c%d7%90%d7%99%d7%99%d7%9d-%d7%94%d7%91%d7%a8%d7%99%d7%98%d7%99%d7%9d/"
    },
    {
      "source": "תרבותו",
      "title": "הים הבלטי",
      "ship": null,
      "ship_normalized": "",
      "date_display": "9 ימים  - נובמבר 2026",
      "date_norm": [
        2026,
        11
      ],
      "price": null,
      "url": "https://tarbutu.co.il/%d7%a7%d7%a8%d7%95%d7%96%d7%99%d7%9d-%d7%91%d7%99%d7%9d-%d7%94%d7%91%d7%9c%d7%98%d7%99/"
    },
    {
      "source": "תרבותו",
      "title": "הפיורדים, הכף הצפוני והארקטי עד שפיצברגן",
      "ship": null,
      "ship_normalized": "",
      "date_display": "9 ימים  - נובמבר 2026",
      "date_norm": [
        2026,
        11
      ],
      "price": null,
      "url": "https://tarbutu.co.il/%d7%a7%d7%a8%d7%95%d7%96%d7%99%d7%9d-%d7%9c%d7%a4%d7%99%d7%95%d7%a8%d7%93%d7%99%d7%9d/"
    },
    {
      "source": "תרבותו",
      "title": "האיים הקנריים",
      "ship": null,
      "ship_normalized": "",
      "date_display": "9 ימים  - נובמבר 2026",
      "date_norm": [
        2026,
        11
      ],
      "price": null,
      "url": "https://tarbutu.co.il/%d7%a7%d7%a8%d7%95%d7%96%d7%99%d7%9d-%d7%9e%d7%90%d7%95%d7%a8%d7%92%d7%a0%d7%99%d7%9d-%d7%9c%d7%90%d7%99%d7%99%d7%9d-%d7%94%d7%a7%d7%a0%d7%a8%d7%99%d7%9d/"
    },
    {
      "source": "תרבותו",
      "title": "קרוז טראנס אטלנטי מאירופה לדרום אמריקה",
      "ship": null,
      "ship_normalized": "",
      "date_display": "9 ימים  - נובמבר 2026",
      "date_norm": [
        2026,
        11
      ],
      "price": null,
      "url": "https://tarbutu.co.il/%d7%98%d7%99%d7%95%d7%9c-%d7%9e%d7%90%d7%95%d7%a8%d7%92%d7%9f-%d7%9e%d7%a9%d7%95%d7%9c%d7%91-%d7%a7%d7%a8%d7%95%d7%96-%d7%98%d7%a8%d7%90%d7%a0%d7%a1-%d7%90%d7%98%d7%9c%d7%a0%d7%98%d7%99-%d7%9e%d7%90/"
    },
    {
      "source": "תרבותו",
      "title": "ארה”ב – ניו אינגלנד ומזרח קנדה",
      "ship": null,
      "ship_normalized": "",
      "date_display": "9 ימים  - נובמבר 2026",
      "date_norm": [
        2026,
        11
      ],
      "price": null,
      "url": "https://tarbutu.co.il/%d7%98%d7%99%d7%95%d7%9c%d7%99%d7%9d-%d7%95%d7%a7%d7%a8%d7%95%d7%96%d7%99%d7%9d-%d7%9c%d7%a0%d7%99%d7%95-%d7%90%d7%99%d7%a0%d7%92%d7%9c%d7%a0%d7%93/"
    },
    {
      "source": "תרבותו",
      "title": "הים התיכון",
      "ship": null,
      "ship_normalized": "",
      "date_display": "9 ימים  - נובמבר 2026",
      "date_norm": [
        2026,
        11
      ],
      "price": null,
      "url": "https://tarbutu.co.il/%d7%a7%d7%a8%d7%95%d7%96%d7%99%d7%9d-%d7%91%d7%99%d7%9d-%d7%94%d7%aa%d7%99%d7%9b%d7%95%d7%9f/"
    },
    {
      "source": "תרבותו",
      "title": "איי סיישל ומדגסקר",
      "ship": null,
      "ship_normalized": "",
      "date_display": "9 ימים  - נובמבר 2026",
      "date_norm": [
        2026,
        11
      ],
      "price": null,
      "url": "https://tarbutu.co.il/%d7%98%d7%99%d7%95%d7%9c-%d7%9e%d7%90%d7%95%d7%a8%d7%92%d7%9f-%d7%a1%d7%99%d7%99%d7%a9%d7%9c-%d7%9e%d7%93%d7%92%d7%a1%d7%a7%d7%a8-%d7%9e%d7%90%d7%95%d7%a8%d7%99%d7%a6%d7%99%d7%95%d7%a1/"
    },
    {
      "source": "תרבותו",
      "title": "הודו והאיים המלדיביים",
      "ship": null,
      "ship_normalized": "",
      "date_display": "9 ימים  - נובמבר 2026",
      "date_norm": [
        2026,
        11
      ],
      "price": null,
      "url": "https://tarbutu.co.il/?p=12047"
    },
    {
      "source": "תרבותו",
      "title": "דרום אמריקה",
      "ship": null,
      "ship_normalized": "",
      "date_display": "9 ימים  - נובמבר 2026",
      "date_norm": [
        2026,
        11
      ],
      "price": null,
      "url": "https://tarbutu.co.il/%d7%a7%d7%a8%d7%95%d7%96%d7%99%d7%9d-%d7%9c%d7%93%d7%a8%d7%95%d7%9d-%d7%90%d7%9e%d7%a8%d7%99%d7%a7%d7%94/"
    },
    {
      "source": "תרבותו",
      "title": "שייט נהרות באירופה",
      "ship": null,
      "ship_normalized": "",
      "date_display": "9 ימים  - נובמבר 2026",
      "date_norm": [
        2026,
        11
      ],
      "price": null,
      "url": "https://tarbutu.co.il/%d7%a9%d7%99%d7%99%d7%98-%d7%a0%d7%94%d7%a8%d7%95%d7%aa-%d7%91%d7%90%d7%99%d7%a8%d7%95%d7%a4%d7%94-%d7%9e%d7%90%d7%95%d7%a8%d7%92%d7%9f/"
    },
    {
      "source": "תרבותו",
      "title": "שייט בדנובה",
      "ship": null,
      "ship_normalized": "",
      "date_display": "9 ימים  - נובמבר 2026",
      "date_norm": [
        2026,
        11
      ],
      "price": null,
      "url": "https://tarbutu.co.il/%d7%93%d7%a0%d7%95%d7%91%d7%94-%d7%9b%d7%9c-%d7%9e%d7%a1%d7%9c%d7%95%d7%9c%d7%99-%d7%94%d7%a9%d7%99%d7%99%d7%98/"
    },
    {
      "source": "תרבותו",
      "title": "שייט על הריין",
      "ship": null,
      "ship_normalized": "",
      "date_display": "9 ימים  - נובמבר 2026",
      "date_norm": [
        2026,
        11
      ],
      "price": null,
      "url": "https://tarbutu.co.il/%d7%a9%d7%99%d7%99%d7%98-%d7%a2%d7%9c-%d7%94%d7%a8%d7%99%d7%99%d7%9f/"
    },
    {
      "source": "תרבותו",
      "title": "דורדון – שייט משולב טיול כוכב",
      "ship": null,
      "ship_normalized": "",
      "date_display": "9 ימים  - נובמבר 2026",
      "date_norm": [
        2026,
        11
      ],
      "price": null,
      "url": "https://tarbutu.co.il/%d7%a9%d7%99%d7%99%d7%98-%d7%91%d7%93%d7%95%d7%a8%d7%93%d7%95%d7%9f-%d7%a4%d7%a8%d7%99%d7%92%d7%95%d7%a8/"
    },
    {
      "source": "תרבותו",
      "title": "נהר הסיין – שייט מנורמנדי לפריז",
      "ship": null,
      "ship_normalized": "",
      "date_display": "9 ימים  - נובמבר 2026",
      "date_norm": [
        2026,
        11
      ],
      "price": null,
      "url": "https://tarbutu.co.il/%d7%90%d7%95%d7%9e%d7%a0%d7%95%d7%aa-%d7%95%d7%a9%d7%90%d7%a0%d7%a1%d7%95%d7%9f-%d7%91%d7%a9%d7%99%d7%99%d7%98-%d7%a2%d7%9c-%d7%a0%d7%94%d7%a8-%d7%94%d7%a1%d7%99%d7%99%d7%9f-%d7%9e%d7%a0%d7%95%d7%a8/"
    },
    {
      "source": "תרבותו",
      "title": "שייט על נהר הדואורו – פורטוגל",
      "ship": null,
      "ship_normalized": "",
      "date_display": "9 ימים  - נובמבר 2026",
      "date_norm": [
        2026,
        11
      ],
      "price": null,
      "url": "https://tarbutu.co.il/%d7%a9%d7%99%d7%99%d7%98-%d7%9e%d7%90%d7%95%d7%a8%d7%92%d7%9f-%d7%a2%d7%9c-%d7%a0%d7%94%d7%a8-%d7%94%d7%93%d7%95%d7%90%d7%95%d7%a8%d7%95-%d7%91%d7%a4%d7%95%d7%a8%d7%98%d7%95%d7%92%d7%9c/"
    },
    {
      "source": "תרבותו",
      "title": "רון והסון – שייט מפרובאנס לבורגונדי",
      "ship": null,
      "ship_normalized": "",
      "date_display": "9 ימים  - נובמבר 2026",
      "date_norm": [
        2026,
        11
      ],
      "price": null,
      "url": "https://tarbutu.co.il/%d7%a9%d7%99%d7%99%d7%98-%d7%a2%d7%9c-%d7%a0%d7%94%d7%a8%d7%95%d7%aa-%d7%94%d7%a1%d7%95%d7%9f-%d7%95%d7%94%d7%a8%d7%95%d7%9f-%d7%9e%d7%a4%d7%a8%d7%95%d7%91%d7%90%d7%a0%d7%a1-%d7%9c%d7%91%d7%95%d7%a8-3/"
    },
    {
      "source": "תרבותו",
      "title": "קרוז משולב טיול",
      "ship": null,
      "ship_normalized": "",
      "date_display": "9 ימים  - נובמבר 2026",
      "date_norm": [
        2026,
        11
      ],
      "price": null,
      "url": "https://tarbutu.co.il/%d7%98%d7%99%d7%95%d7%9c%d7%99%d7%9d-%d7%a7%d7%a8%d7%95%d7%96/"
    },
    {
      "source": "תרבותו",
      "title": "הודו והאיים המלדיביים",
      "ship": null,
      "ship_normalized": "",
      "date_display": "9 ימים  - נובמבר 2026",
      "date_norm": [
        2026,
        11
      ],
      "price": null,
      "url": "https://tarbutu.co.il/%d7%98%d7%99%d7%95%d7%9c-%d7%9e%d7%90%d7%95%d7%a8%d7%92%d7%9f-%d7%9c%d7%94%d7%95%d7%93%d7%95-%d7%a7%d7%a8%d7%95%d7%96-%d7%9c%d7%90%d7%99%d7%99%d7%9d-%d7%94%d7%9e%d7%9c%d7%93%d7%99%d7%91%d7%99%d7%99/"
    },
    {
      "source": "תרבותו",
      "title": "טיולי חורף",
      "ship": null,
      "ship_normalized": "",
      "date_display": "9 ימים  - נובמבר 2026",
      "date_norm": [
        2026,
        11
      ],
      "price": null,
      "url": "https://tarbutu.co.il/%d7%98%d7%99%d7%95%d7%9c%d7%99-%d7%97%d7%95%d7%a8%d7%a3/"
    },
    {
      "source": "תרבותו",
      "title": "לפלנד – ספארי חורף",
      "ship": null,
      "ship_normalized": "",
      "date_display": "9 ימים  - נובמבר 2026",
      "date_norm": [
        2026,
        11
      ],
      "price": null,
      "url": "https://tarbutu.co.il/%d7%98%d7%99%d7%95%d7%9c-%d7%9b%d7%95%d7%9b%d7%91-%d7%9c%d7%9c%d7%a4%d7%9c%d7%a0%d7%93/"
    },
    {
      "source": "תרבותו",
      "title": "האיים הקנריים",
      "ship": null,
      "ship_normalized": "",
      "date_display": "9 ימים  - נובמבר 2026",
      "date_norm": [
        2026,
        11
      ],
      "price": null,
      "url": "https://tarbutu.co.il/%d7%a7%d7%a8%d7%95%d7%96-%d7%9e%d7%90%d7%95%d7%a8%d7%92%d7%9f-%d7%9c%d7%90%d7%99%d7%99%d7%9d-%d7%94%d7%a7%d7%a0%d7%a8%d7%99%d7%99%d7%9d-%d7%9e%d7%93%d7%99%d7%99%d7%a8%d7%94-%d7%95%d7%a1%d7%a4%d7%a8/"
    },
    {
      "source": "תרבותו",
      "title": "כל הטיולים",
      "ship": null,
      "ship_normalized": "",
      "date_display": "9 ימים  - נובמבר 2026",
      "date_norm": [
        2026,
        11
      ],
      "price": null,
      "url": "https://tarbutu.co.il/alltours/"
    },
    {
      "source": "תרבותו",
      "title": "תנאים כלליים",
      "ship": null,
      "ship_normalized": "",
      "date_display": "9 ימים  - נובמבר 2026",
      "date_norm": [
        2026,
        11
      ],
      "price": null,
      "url": "https://tarbutu.co.il/%d7%aa%d7%a0%d7%90%d7%99%d7%9d-2/"
    },
    {
      "source": "תרבותו",
      "title": "צור קשר",
      "ship": null,
      "ship_normalized": "",
      "date_display": "9 ימים  - נובמבר 2026",
      "date_norm": [
        2026,
        11
      ],
      "price": null,
      "url": "https://tarbutu.co.il/%d7%a6%d7%95%d7%a8-%d7%a7%d7%a9%d7%a8-%d7%aa%d7%a8%d7%91%d7%95%d7%aa%d7%95/"
    },
    {
      "source": "תרבותו",
      "title": "משובים",
      "ship": null,
      "ship_normalized": "",
      "date_display": "9 ימים  - נובמבר 2026",
      "date_norm": [
        2026,
        11
      ],
      "price": null,
      "url": "https://tarbutu.co.il/reviews/"
    },
    {
      "source": "תרבותו",
      "title": "אודות",
      "ship": null,
      "ship_normalized": "",
      "date_display": "9 ימים  - נובמבר 2026",
      "date_norm": [
        2026,
        11
      ],
      "price": null,
      "url": "https://tarbutu.co.il/%d7%90%d7%95%d7%93%d7%95%d7%aa/"
    },
    {
      "source": "תרבותו",
      "title": "עתונות",
      "ship": null,
      "ship_normalized": "",
      "date_display": "9 ימים  - נובמבר 2026",
      "date_norm": [
        2026,
        11
      ],
      "price": null,
      "url": "https://tarbutu.co.il/%d7%9b%d7%aa%d7%91%d7%95-%d7%a2%d7%9c%d7%99%d7%a0%d7%95/"
    },
    {
      "source": "תרבותו",
      "title": "דף הבית",
      "ship": null,
      "ship_normalized": "",
      "date_display": "9 ימים  - נובמבר 2026",
      "date_norm": [
        2026,
        11
      ],
      "price": null,
      "url": "https://tarbutu.co.il/"
    },
    {
      "source": "תרבותו",
      "title": "המדריכים שלנו",
      "ship": null,
      "ship_normalized": "",
      "date_display": "9 ימים  - נובמבר 2026",
      "date_norm": [
        2026,
        11
      ],
      "price": null,
      "url": "https://tarbutu.co.il/madrih/"
    },
    {
      "source": "תרבותו",
      "title": "לאיזור האישי",
      "ship": null,
      "ship_normalized": "",
      "date_display": "9 ימים  - נובמבר 2026",
      "date_norm": [
        2026,
        11
      ],
      "price": null,
      "url": "https://clients.tarbutu.co.il/"
    },
    {
      "source": "תרבותו",
      "title": "טיול מורשת תעופה בצ'כיה והקשר לחיל האוויר הישראלי",
      "ship": null,
      "ship_normalized": "",
      "date_display": "9 ימים  - נובמבר 2026",
      "date_norm": [
        2026,
        11
      ],
      "price": null,
      "url": "https://tarbutu.co.il/%d7%98%d7%99%d7%95%d7%9c-%d7%9e%d7%90%d7%95%d7%a8%d7%92%d7%9f-%d7%9c%d7%a6%d7%9b%d7%99%d7%94-%d7%a2%d7%95%d7%9c%d7%9d-%d7%94%d7%aa%d7%a2%d7%95%d7%a4%d7%94/"
    },
    {
      "source": "תרבותו",
      "title": "סרדיניה-טיול עומק כולל קרנבל המסכות",
      "ship": null,
      "ship_normalized": "",
      "date_display": "9 ימים  - נובמבר 2026",
      "date_norm": [
        2026,
        11
      ],
      "price": null,
      "url": "https://tarbutu.co.il/%d7%98%d7%99%d7%95%d7%9c-%d7%9e%d7%90%d7%95%d7%a8%d7%92%d7%9f-%d7%9c%d7%a1%d7%a8%d7%93%d7%99%d7%a0%d7%99%d7%94/"
    },
    {
      "source": "תרבותו",
      "title": "סמינר מטייל בוונציה בימי קרנבל המסכות",
      "ship": null,
      "ship_normalized": "",
      "date_display": "9 ימים  - נובמבר 2026",
      "date_norm": [
        2026,
        11
      ],
      "price": null,
      "url": "https://tarbutu.co.il/%d7%a1%d7%9e%d7%99%d7%a0%d7%a8-%d7%9e%d7%98%d7%99%d7%99%d7%9c-%d7%9c%d7%95%d7%a0%d7%a6%d7%99%d7%94-%d7%91%d7%a7%d7%a8%d7%a0%d7%91%d7%9c-2/"
    },
    {
      "source": "תרבותו",
      "title": "אקוודור, אמזונס ושייט יאכטה באיי גלאפגוס",
      "ship": null,
      "ship_normalized": "",
      "date_display": "9 ימים  - נובמבר 2026",
      "date_norm": [
        2026,
        11
      ],
      "price": null,
      "url": "https://tarbutu.co.il/%d7%98%d7%99%d7%95%d7%9c-%d7%9e%d7%90%d7%95%d7%a8%d7%92%d7%9f-%d7%9c%d7%93%d7%a8%d7%95%d7%9d-%d7%90%d7%9e%d7%a8%d7%99%d7%a7%d7%94-%d7%9b%d7%95%d7%9c%d7%9c-%d7%a9%d7%99%d7%99%d7%98-%d7%99%d7%90%d7%9b-5/"
    },
    {
      "source": "תרבותו",
      "title": "איחוד האמירויות – 7 ימים",
      "ship": null,
      "ship_normalized": "",
      "date_display": "9 ימים  - נובמבר 2026",
      "date_norm": [
        2026,
        11
      ],
      "price": null,
      "url": "https://tarbutu.co.il/%d7%98%d7%99%d7%95%d7%9c-%d7%9e%d7%90%d7%95%d7%a8%d7%92%d7%9f-%d7%9c%d7%90%d7%99%d7%97%d7%95%d7%93-%d7%94%d7%90%d7%9e%d7%99%d7%a8%d7%95%d7%99%d7%95%d7%aa-5/"
    },
    {
      "source": "תרבותו",
      "title": "אלזס-לוריין וקהילות שו\"ם שעל נהר הריין בדגש תרבות יהודית",
      "ship": null,
      "ship_normalized": "",
      "date_display": "9 ימים  - נובמבר 2026",
      "date_norm": [
        2026,
        11
      ],
      "price": null,
      "url": "https://tarbutu.co.il/__trashed-2-2-2/"
    },
    {
      "source": "תרבותו",
      "title": "הרי הפירנאים, ארץ הבסקים, בורדו",
      "ship": null,
      "ship_normalized": "",
      "date_display": "9 ימים  - נובמבר 2026",
      "date_norm": [
        2026,
        11
      ],
      "price": null,
      "url": "https://tarbutu.co.il/__trashed-2-2/"
    },
    {
      "source": "תרבותו",
      "title": "סמינר מטייל בארצות הבלטיות בקורטוב של יידישקַיְיט",
      "ship": null,
      "ship_normalized": "",
      "date_display": "9 ימים  - נובמבר 2026",
      "date_norm": [
        2026,
        11
      ],
      "price": null,
      "url": "https://tarbutu.co.il/%d7%a1%d7%9e%d7%99%d7%a0%d7%a8-%d7%9e%d7%98%d7%99%d7%99%d7%9c-%d7%91%d7%90%d7%a8%d7%a6%d7%95%d7%aa-%d7%94%d7%91%d7%9c%d7%98%d7%99%d7%95%d7%aa-%d7%91%d7%a7%d7%95%d7%a8%d7%98%d7%95%d7%91-%d7%a9%d7%9c/"
    },
    {
      "source": "תרבותו",
      "title": "צפון קוריאה וחבל מנצ’וריה",
      "ship": null,
      "ship_normalized": "",
      "date_display": "9 ימים  - נובמבר 2026",
      "date_norm": [
        2026,
        11
      ],
      "price": null,
      "url": "https://tarbutu.co.il/%d7%98%d7%99%d7%95%d7%9c-%d7%9e%d7%90%d7%95%d7%a8%d7%92%d7%9f-%d7%9c%d7%a6%d7%a4%d7%95%d7%9f-%d7%a7%d7%95%d7%a8%d7%99%d7%90%d7%94-%d7%95%d7%97%d7%91%d7%9c-%d7%9e%d7%a0%d7%a6%d7%95%d7%a8%d7%99%d7%94-3/"
    },
    {
      "source": "תרבותו",
      "title": "אלסקה והרי הרוקי בקנדה",
      "ship": null,
      "ship_normalized": "",
      "date_display": "9 ימים  - נובמבר 2026",
      "date_norm": [
        2026,
        11
      ],
      "price": null,
      "url": "https://tarbutu.co.il/%d7%a7%d7%a8%d7%95%d7%96-%d7%9c%d7%a7%d7%a0%d7%93%d7%94-%d7%9e%d7%a2%d7%a8%d7%91-%d7%95%d7%90%d7%9c%d7%a1%d7%a7%d7%94/"
    },
    {
      "source": "תרבותו",
      "title": "ארה\"ב ומזרח קנדה-שלכת בניו אינגלנד",
      "ship": null,
      "ship_normalized": "",
      "date_display": "9 ימים  - נובמבר 2026",
      "date_norm": [
        2026,
        11
      ],
      "price": null,
      "url": "https://tarbutu.co.il/%d7%98%d7%99%d7%95%d7%9c-%d7%9e%d7%90%d7%95%d7%a8%d7%92%d7%9f-%d7%9e%d7%a9%d7%95%d7%9c%d7%91-%d7%91%d7%a7%d7%a8%d7%95%d7%96-%d7%91%d7%a0%d7%99%d7%95-%d7%90%d7%99%d7%a0%d7%92%d7%9c%d7%a0%d7%93/"
    },
    {
      "source": "תרבותו",
      "title": "האיים הבריטיים",
      "ship": null,
      "ship_normalized": "",
      "date_display": "9 ימים  - נובמבר 2026",
      "date_norm": [
        2026,
        11
      ],
      "price": null,
      "url": "https://tarbutu.co.il/%d7%a7%d7%a8%d7%95%d7%96%d7%99%d7%9d-%d7%9c%d7%90%d7%99%d7%99%d7%9d-%d7%94%d7%91%d7%a8%d7%99%d7%98%d7%99%d7%9d-2-2/"
    },
    {
      "source": "תרבותו",
      "title": "הפיורדים הנורווגיים",
      "ship": null,
      "ship_normalized": "",
      "date_display": "9 ימים  - נובמבר 2026",
      "date_norm": [
        2026,
        11
      ],
      "price": null,
      "url": "https://tarbutu.co.il/%d7%a4%d7%99%d7%95%d7%a8%d7%93%d7%99%d7%9d2/"
    },
    {
      "source": "תרבותו",
      "title": "הפיורדים והכף הצפוני",
      "ship": null,
      "ship_normalized": "",
      "date_display": "9 ימים  - נובמבר 2026",
      "date_norm": [
        2026,
        11
      ],
      "price": null,
      "url": "https://tarbutu.co.il/%d7%94%d7%9b%d7%a3-%d7%94%d7%a6%d7%a4%d7%95%d7%a0%d7%99/"
    },
    {
      "source": "תרבותו",
      "title": "החוג הארקטי, מעבר לכף הצפוני  עד לשפיצברגן",
      "ship": null,
      "ship_normalized": "",
      "date_display": "9 ימים  - נובמבר 2026",
      "date_norm": [
        2026,
        11
      ],
      "price": null,
      "url": "https://tarbutu.co.il/%d7%a7%d7%a8%d7%95%d7%96-%d7%9e%d7%90%d7%95%d7%a8%d7%92%d7%9f-%d7%9c%d7%97%d7%95%d7%92-%d7%94%d7%90%d7%a8%d7%a7%d7%98%d7%99-%d7%9e%d7%a2%d7%91%d7%a8-%d7%9c%d7%9b%d7%a3-%d7%94%d7%a6%d7%a4%d7%95%d7%a0/"
    },
    {
      "source": "תרבותו",
      "title": "יפן והמזרח הרחוק",
      "ship": null,
      "ship_normalized": "",
      "date_display": "9 ימים  - נובמבר 2026",
      "date_norm": [
        2026,
        11
      ],
      "price": null,
      "url": "https://tarbutu.co.il/%d7%98%d7%99%d7%95%d7%9c%d7%99%d7%9d-%d7%9c%d7%99%d7%a4%d7%9f-%d7%95%d7%9c%d7%9e%d7%96%d7%a8%d7%97-%d7%94%d7%a8%d7%97%d7%95%d7%a7/"
    },
    {
      "source": "תרבותו",
      "title": "טיול וקרוז לאלסקה ולהרי הרוקי אוגוסט 2026",
      "ship": null,
      "ship_normalized": "",
      "date_display": "9 ימים  - נובמבר 2026",
      "date_norm": [
        2026,
        11
      ],
      "price": null,
      "url": "https://tarbutu.co.il/https-tarbutu-co-il-wp-admin-post-phpactioneditpost30133/"
    },
    {
      "source": "תרבותו",
      "title": "פניני הים האדריאטי -דוברובניק, מונטנגרו, קורפו",
      "ship": null,
      "ship_normalized": "",
      "date_display": "9 ימים  - נובמבר 2026",
      "date_norm": [
        2026,
        11
      ],
      "price": null,
      "url": "https://tarbutu.co.il/%d7%a7%d7%a8%d7%95%d7%96-%d7%9e%d7%90%d7%95%d7%a8%d7%92%d7%9f-%d7%91%d7%9e%d7%96%d7%a8%d7%97-%d7%94%d7%99%d7%9d-%d7%94%d7%aa%d7%99%d7%9b%d7%95%d7%9f-%d7%9b%d7%95%d7%9c%d7%9c-%d7%95%d7%a0%d7%a6%d7%99/"
    },
    {
      "source": "תרבותו",
      "title": "הודו קרוז לאיים המלדיביים",
      "ship": null,
      "ship_normalized": "",
      "date_display": "9 ימים  - נובמבר 2026",
      "date_norm": [
        2026,
        11
      ],
      "price": null,
      "url": "https://tarbutu.co.il/%d7%98%d7%99%d7%95%d7%9c-%d7%9e%d7%90%d7%95%d7%a8%d7%92%d7%9f-%d7%9c%d7%94%d7%95%d7%93%d7%95-%d7%a7%d7%a8%d7%95%d7%96-%d7%9c%d7%90%d7%99%d7%99%d7%9d-%d7%94%d7%9e%d7%9c%d7%93%d7%99%d7%91%d7%99%d7%99-3/"
    },
    {
      "source": "תרבותו",
      "title": "איי סיישל, מדגסקר, מאוריציוס וריוניון",
      "ship": null,
      "ship_normalized": "",
      "date_display": "9 ימים  - נובמבר 2026",
      "date_norm": [
        2026,
        11
      ],
      "price": null,
      "url": "https://tarbutu.co.il/%d7%98%d7%99%d7%95%d7%9c-%d7%9e%d7%90%d7%95%d7%a8%d7%92%d7%9f-%d7%a1%d7%99%d7%99%d7%a9%d7%9c-%d7%9e%d7%93%d7%92%d7%a1%d7%a7%d7%a8-%d7%9e%d7%90%d7%95%d7%a8%d7%99%d7%a6%d7%99%d7%95%d7%a1-2-2-2/"
    },
    {
      "source": "תרבותו",
      "title": "קרוזים לניו אינגלנד",
      "ship": null,
      "ship_normalized": "",
      "date_display": "9 ימים  - נובמבר 2026",
      "date_norm": [
        2026,
        11
      ],
      "price": null,
      "url": "https://tarbutu.co.il/%d7%a0%d7%99%d7%95-%d7%90%d7%99%d7%a0%d7%92%d7%9c%d7%a0%d7%93/"
    },
    {
      "source": "תרבותו",
      "title": "שייט על נהר הרון בצרפת–מפרובאנס לליון",
      "ship": null,
      "ship_normalized": "",
      "date_display": "9 ימים  - נובמבר 2026",
      "date_norm": [
        2026,
        11
      ],
      "price": null,
      "url": "https://tarbutu.co.il/%d7%a0%d7%94%d7%a8%d7%95%d7%aa-%d7%a1%d7%95%d7%9f-%d7%95%d7%a8%d7%95%d7%9f-%d7%9b%d7%9c-%d7%9e%d7%a1%d7%9c%d7%95%d7%9c%d7%99-%d7%94%d7%a9%d7%99%d7%99%d7%98-2/"
    },
    {
      "source": "תרבותו",
      "title": "שייט על נהר הדואורו בפורטוגל",
      "ship": null,
      "ship_normalized": "",
      "date_display": "9 ימים  - נובמבר 2026",
      "date_norm": [
        2026,
        11
      ],
      "price": null,
      "url": "https://tarbutu.co.il/%d7%a9%d7%99%d7%99%d7%98-%d7%a2%d7%9c-%d7%a0%d7%94%d7%a8-%d7%94%d7%93%d7%95%d7%90%d7%95%d7%a8%d7%95-%d7%91%d7%a4%d7%95%d7%a8%d7%98%d7%95%d7%92%d7%9c/"
    },
    {
      "source": "תרבותו",
      "title": "שייט על הדנובה בתקופת שוקי חג המולד",
      "ship": null,
      "ship_normalized": "",
      "date_display": "9 ימים  - נובמבר 2026",
      "date_norm": [
        2026,
        11
      ],
      "price": null,
      "url": "https://tarbutu.co.il/https-tarbutu-co-il-wp-admin-post-phpactioneditpost32515/"
    },
    {
      "source": "תרבותו",
      "title": "שייט על הריין לשוקי חג המולד",
      "ship": null,
      "ship_normalized": "",
      "date_display": "9 ימים  - נובמבר 2026",
      "date_norm": [
        2026,
        11
      ],
      "price": null,
      "url": "https://tarbutu.co.il/%d7%a9%d7%99%d7%99%d7%98-%d7%a2%d7%9c-%d7%94%d7%a8%d7%99%d7%99%d7%9f-2/"
    },
    {
      "source": "תרבותו",
      "title": "שייט נהר הסיין – מפריז לנורמנדי וחופי הנחיתה",
      "ship": null,
      "ship_normalized": "",
      "date_display": "9 ימים  - נובמבר 2026",
      "date_norm": [
        2026,
        11
      ],
      "price": null,
      "url": "https://tarbutu.co.il/%d7%a9%d7%99%d7%99%d7%98-%d7%a2%d7%9c-%d7%a0%d7%94%d7%a8-%d7%94%d7%a1%d7%99%d7%99%d7%9f/"
    },
    {
      "source": "תרבותו",
      "title": "כל שייט נהרות צרפת ופורטוגל",
      "ship": null,
      "ship_normalized": "",
      "date_display": "9 ימים  - נובמבר 2026",
      "date_norm": [
        2026,
        11
      ],
      "price": null,
      "url": "https://tarbutu.co.il/%d7%a0%d7%94%d7%a8%d7%95%d7%aa-%d7%a1%d7%95%d7%9f-%d7%95%d7%a8%d7%95%d7%9f-%d7%9b%d7%9c-%d7%9e%d7%a1%d7%9c%d7%95%d7%9c%d7%99-%d7%94%d7%a9%d7%99%d7%99%d7%98-2-2/"
    },
    {
      "source": "תרבותו",
      "title": "שייט בווייטנאם וקמבודיה על נהר המקונג",
      "ship": null,
      "ship_normalized": "",
      "date_display": "9 ימים  - נובמבר 2026",
      "date_norm": [
        2026,
        11
      ],
      "price": null,
      "url": "https://tarbutu.co.il/%d7%a7%d7%a8%d7%95%d7%96-%d7%91%d7%95%d7%99%d7%98%d7%a0%d7%90%d7%9d-%d7%95%d7%a7%d7%9e%d7%91%d7%95%d7%93%d7%99%d7%94-%d7%a2%d7%9c-%d7%a0%d7%94%d7%a8-%d7%94%d7%9e%d7%a7%d7%95%d7%a0%d7%92-%d7%91%d7%a1/"
    },
    {
      "source": "תרבותו",
      "title": "שייט על הדנובה – כל מסלולי השייט",
      "ship": null,
      "ship_normalized": "",
      "date_display": "9 ימים  - נובמבר 2026",
      "date_norm": [
        2026,
        11
      ],
      "price": null,
      "url": "https://tarbutu.co.il/%d7%93%d7%a0%d7%95%d7%91%d7%94-%d7%9b%d7%9c-%d7%9e%d7%a1%d7%9c%d7%95%d7%9c%d7%99-%d7%94%d7%a9%d7%99%d7%99%d7%98-2/"
    },
    {
      "source": "תרבותו",
      "title": "שייט על הדנובה עד ל\"קניון שערי הברזל\"",
      "ship": null,
      "ship_normalized": "",
      "date_display": "9 ימים  - נובמבר 2026",
      "date_norm": [
        2026,
        11
      ],
      "price": null,
      "url": "https://tarbutu.co.il/%d7%a9%d7%99%d7%99%d7%98-%d7%a2%d7%9c-%d7%94%d7%93%d7%a0%d7%95%d7%91%d7%94-%d7%a2%d7%93-%d7%9c%d7%a9%d7%a2%d7%a8%d7%99-%d7%94%d7%91%d7%a8%d7%96%d7%9c-3/"
    },
    {
      "source": "תרבותו",
      "title": "שייט וטיול בין ארמונות עמק הלואר",
      "ship": null,
      "ship_normalized": "",
      "date_display": "9 ימים  - נובמבר 2026",
      "date_norm": [
        2026,
        11
      ],
      "price": null,
      "url": "https://tarbutu.co.il/%d7%98%d7%99%d7%95%d7%9c-%d7%a9%d7%99%d7%99%d7%98-%d7%a2%d7%9e%d7%a7-%d7%9c%d7%95%d7%90%d7%a8-3-2-3-2-4/"
    },
    {
      "source": "תרבותו",
      "title": "קרוז למזרח הרחוק – סין, יפן, הונג קונג, וייטנאם וסינגפור",
      "ship": null,
      "ship_normalized": "",
      "date_display": "9 ימים  - נובמבר 2026",
      "date_norm": [
        2026,
        11
      ],
      "price": null,
      "url": "https://tarbutu.co.il/?p=24141"
    },
    {
      "source": "תרבותו",
      "title": "המזרח הרחוק – הונג קונג, טייוואן, יפן, דרום קוריאה, סין",
      "ship": null,
      "ship_normalized": "",
      "date_display": "9 ימים  - נובמבר 2026",
      "date_norm": [
        2026,
        11
      ],
      "price": null,
      "url": "https://tarbutu.co.il/?p=22558"
    },
    {
      "source": "תרבותו",
      "title": "שייט על נהר הריין לשוקי חג המולד בספינת הנהר Ms-Symphonie",
      "ship": "Ms-Symphonie",
      "ship_normalized": "ms-symphonie",
      "date_display": "9 ימים  - נובמבר 2026",
      "date_norm": [
        2026,
        11
      ],
      "price": null,
      "url": "https://tarbutu.co.il/8-%d7%99%d7%9e%d7%99-%d7%98%d7%99%d7%95%d7%9c-%d7%9e%d7%a9%d7%95%d7%9c%d7%91%d7%99%d7%9d-%d7%91%d7%a9%d7%99%d7%99%d7%98-%d7%a2%d7%9c-%d7%94%d7%a8%d7%99%d7%99%d7%9f-3/"
    },
    {
      "source": "תרבותו",
      "title": "איחוד האמירויות – טיול ל-7 האמירויות",
      "ship": null,
      "ship_normalized": "",
      "date_display": "9 ימים  - נובמבר 2026",
      "date_norm": [
        2026,
        11
      ],
      "price": null,
      "url": "https://tarbutu.co.il/?p=24789"
    },
    {
      "source": "תרבותו",
      "title": "קרנבל המסיכות בוונציה",
      "ship": null,
      "ship_normalized": "",
      "date_display": "9 ימים  - נובמבר 2026",
      "date_norm": [
        2026,
        11
      ],
      "price": null,
      "url": "https://tarbutu.co.il/?p=12886"
    },
    {
      "source": "תרבותו",
      "title": "שייט באיי גלאפגוס, אקוודור ואמזונס",
      "ship": null,
      "ship_normalized": "",
      "date_display": "9 ימים  - נובמבר 2026",
      "date_norm": [
        2026,
        11
      ],
      "price": null,
      "url": "https://tarbutu.co.il/?p=19848"
    },
    {
      "source": "תרבותו",
      "title": "קרוז טראנס אטלנטי מספרד והאיים הקנריים לדרום אמריקה",
      "ship": null,
      "ship_normalized": "",
      "date_display": "9 ימים  - נובמבר 2026",
      "date_norm": [
        2026,
        11
      ],
      "price": null,
      "url": "https://tarbutu.co.il/%d7%98%d7%99%d7%95%d7%9c-%d7%9e%d7%90%d7%95%d7%a8%d7%92%d7%9f-%d7%9e%d7%a9%d7%95%d7%9c%d7%91-%d7%a7%d7%a8%d7%95%d7%96-%d7%98%d7%a8%d7%90%d7%a0%d7%a1-%d7%90%d7%98%d7%9c%d7%a0%d7%98%d7%99-%d7%9e%d7%90-2/"
    },
    {
      "source": "תרבותו",
      "title": "טיול עומק יבשתי לאוסטרליה ולניו זילנד – חלום גן העדן",
      "ship": null,
      "ship_normalized": "",
      "date_display": "9 ימים  - נובמבר 2026",
      "date_norm": [
        2026,
        11
      ],
      "price": null,
      "url": "https://tarbutu.co.il/?p=29409"
    },
    {
      "source": "תרבותו",
      "title": "קרוז מאורגן למערב הים התיכון באוניה המפוארת והחדשנית בעולם הקרוזים 2026 Msc World Europa",
      "ship": "World Europa",
      "ship_normalized": "world europa",
      "date_display": "9 ימים  - נובמבר 2026",
      "date_norm": [
        2026,
        11
      ],
      "price": null,
      "url": "https://tarbutu.co.il/%d7%a7%d7%a8%d7%95%d7%96-%d7%9e%d7%90%d7%95%d7%a8%d7%92%d7%9f-%d7%91%d7%9e%d7%a2%d7%a8%d7%91-%d7%94%d7%99%d7%9d-%d7%94%d7%aa%d7%99%d7%9b%d7%95%d7%9f-%d7%9b%d7%95%d7%9c%d7%9c-%d7%a1%d7%99%d7%a6%d7%99-7/"
    },
    {
      "source": "תרבותו",
      "title": "קרוז לאלסקה וטיול להרי הרוקי במערב קנדה",
      "ship": null,
      "ship_normalized": "",
      "date_display": "9 ימים  - נובמבר 2026",
      "date_norm": [
        2026,
        11
      ],
      "price": null,
      "url": "https://tarbutu.co.il/https-tarbutu-co-il-wp-admin-post-phpactioneditpost33459/"
    },
    {
      "source": "תרבותו",
      "title": "קרוזים מאורגנים לפניני הים האדריאטי ספטמבר 2026",
      "ship": null,
      "ship_normalized": "",
      "date_display": "10 ימים -   ספטמבר 2026",
      "date_norm": [
        2026,
        9
      ],
      "price": null,
      "url": "https://tarbutu.co.il/%d7%a7%d7%a8%d7%95%d7%96-%d7%9e%d7%90%d7%95%d7%a8%d7%92%d7%9f-%d7%91%d7%9e%d7%96%d7%a8%d7%97-%d7%94%d7%99%d7%9d-%d7%94%d7%aa%d7%99%d7%9b%d7%95%d7%9f-%d7%9b%d7%95%d7%9c%d7%9c-%d7%95%d7%a0%d7%a6%d7%99/"
    },
    {
      "source": "תרבותו",
      "title": "טיול משולב קרוז לאלסקה ולהרי הרוקי אוגוסט 2026טיול עוצמתי המשלב בין טבע פראי ונופים מדהימים לבין תרבות עשירה וחוויות ייחודיות. הצטרפו אלינו למסע בלתי נשכח שייקח אתכם לפינות החמד ביותר של קנדה ואלסקה, ויחשוף בפניכם את הפלאים הטבעיים והתרבותיים המרהיבים של האזור",
      "ship": null,
      "ship_normalized": "",
      "date_display": "18 ימים - 19 באוגוסט 2026",
      "date_norm": [
        2026,
        8
      ],
      "price": null,
      "url": "https://tarbutu.co.il/https-tarbutu-co-il-wp-admin-post-phpactioneditpost30133/"
    },
    {
      "source": "תרבותו",
      "title": "טיול מאורגן להודו קרוז לאיים המלדיביים",
      "ship": null,
      "ship_normalized": "",
      "date_display": "17 ימים - דצמבר 2026",
      "date_norm": [
        2026,
        12
      ],
      "price": null,
      "url": "https://tarbutu.co.il/%d7%98%d7%99%d7%95%d7%9c-%d7%9e%d7%90%d7%95%d7%a8%d7%92%d7%9f-%d7%9c%d7%94%d7%95%d7%93%d7%95-%d7%a7%d7%a8%d7%95%d7%96-%d7%9c%d7%90%d7%99%d7%99%d7%9d-%d7%94%d7%9e%d7%9c%d7%93%d7%99%d7%91%d7%99%d7%99-3/"
    },
    {
      "source": "תרבותו",
      "title": "קרוזים באירופה",
      "ship": null,
      "ship_normalized": "",
      "date_display": "9 ימים  - נובמבר 2026",
      "date_norm": [
        2026,
        11
      ],
      "price": null,
      "url": "https://tarbutu.co.il/%d7%a7%d7%a8%d7%95%d7%96%d7%99%d7%9d-%d7%91%d7%90%d7%99%d7%a8%d7%95%d7%a4%d7%94/"
    },
    {
      "source": "תרבותו",
      "title": "שייט אוניות גדולות",
      "ship": null,
      "ship_normalized": "",
      "date_display": "9 ימים  - נובמבר 2026",
      "date_norm": [
        2026,
        11
      ],
      "price": null,
      "url": "https://tarbutu.co.il/%d7%a7%d7%a8%d7%95%d7%96%d7%99%d7%9d-%d7%9e%d7%90%d7%95%d7%a8%d7%92%d7%a0%d7%99%d7%9d/"
    },
    {
      "source": "תרבותו",
      "title": "שייט על נהר הסיין",
      "ship": null,
      "ship_normalized": "",
      "date_display": "9 ימים  - נובמבר 2026",
      "date_norm": [
        2026,
        11
      ],
      "price": null,
      "url": "https://tarbutu.co.il/שייט-על-נהר-הסיין/"
    },
    {
      "source": "תרבותו",
      "title": "כתבות ומדריכים",
      "ship": null,
      "ship_normalized": "",
      "date_display": "9 ימים  - נובמבר 2026",
      "date_norm": [
        2026,
        11
      ],
      "price": null,
      "url": "https://tarbutu.co.il/%d7%9e%d7%99%d7%93%d7%a2-%d7%a2%d7%9c-%d7%98%d7%99%d7%95%d7%9c%d7%99%d7%9d/"
    }
  ],
  "massaot_cruises": [],
  "matches": []
}